PyGameKit/__init__.py
PyGameKit/main.py
PyGameKit-0.2.dist-info/METADATA
PyGameKit-0.2.dist-info/WHEEL
PyGameKit-0.2.dist-info/top_level.txt
PyGameKit-0.2.dist-info/RECORD
