Metadata-Version: 2.1
Name: PyGameKit
Version: 0.2
Summary: A PyGame wrapper for pygame-ce
Requires-Dist: pygame-ce
